<xml xmlns="http://www.w3.org/1999/xhtml"><block type="variables_set" id=",p}edPe-31Z`W|O[QoAq" x="-115" y="-704"><field name="VAR">ball speed</field><value name="VALUE"><block type="math_number" id="?imJBH1i7[yXwm;n9-jS"><field name="NUM">5</field></block></value><next><block type="set_timeout" id="Rme_;,|S7NN_;WdvO]g)"><field name="timeout">500</field><statement name="statements"><block type="variables_set" id="?1X;Nd#{nxnA3du=iQ{;"><field name="VAR">should go</field><value name="VALUE"><block type="logic_boolean" id="T0y=9^Lpof%p~LGf)B6@"><field name="BOOL">TRUE</field></block></value><next><block type="procedures_callnoreturn" id="W{dqwOm53m%_$tv5BNy~"><mutation name="reset ball"></mutation><next><block type="sprite_set_x" id=".qMd}lhslXAtN:srLGXh"><field name="NAME">paddle</field><value name="value"><block type="math_arithmetic" id="KA{%gw(A8`XbJA]QqUcx"><field name="OP">MINUS</field><value name="A"><shadow type="math_number" id="xmcD67+xO|$JXdU}##k^"><field name="NUM">1</field></shadow><block type="math_arithmetic" id="mq/DXsm@(9v(~L/A{5ue"><field name="OP">DIVIDE</field><value name="A"><shadow type="math_number" id="4(R-`K$u5SK.T[enmlGA"><field name="NUM">1</field></shadow><block type="canvas_get_width" id="A.|_BM#Q?ggP~Q?RF{wG"><field name="NAME">canvas</field></block></value><value name="B"><shadow type="math_number" id="a9p8v0JUl@UVg!!#PR!@"><field name="NUM">2</field></shadow></value></block></value><value name="B"><shadow type="math_number" id="Y]HzQqnnYn`0nvls`/g:"><field name="NUM">50</field></shadow></value></block></value><next><block type="sprite_set_y" id="pl{iMX^r.lCzQy{rBj0`"><field name="NAME">paddle</field><value name="value"><block type="math_arithmetic" id="!OM:s=v~/@ewf[xt9:xW"><field name="OP">MINUS</field><value name="A"><shadow type="math_number" id="i1N0{njUp,LnCU.N?^%L"><field name="NUM">1</field></shadow><block type="canvas_get_height" id="_TV?Jy/P({^mQKZG,vQb"><field name="NAME">canvas</field></block></value><value name="B"><shadow type="math_number" id="@=:PQuN^7ZB6UB0Aq/VD"><field name="NUM">20</field></shadow></value></block></value><next><block type="set_interval" id=".j}oPzz$n3P*kRY{t2gv"><field name="timeout">25</field><comment pinned="false" h="80" w="160">this is our main game loop, where we bounce the ball</comment><statement name="statements"><block type="controls_if" id="x!OT.tbHI*z3bvlt]}NI"><value name="IF0"><block type="variables_get" id="=DyW)b6V1LoNf*c_2snx"><field name="VAR">should go</field></block></value><statement name="DO0"><block type="sprite_intersect_edge_bounce" id="03?yKP$ex[rbi9dRZ9jI"><field name="NAME">ball</field><field name="edgetype">horizontal</field><value name="speed"><block type="variables_get" id="dH@v.*Js3w6_x#+*4mq%"><field name="VAR">ball speed</field></block></value><next><block type="sprite_intersect_edge_bounce" id="tmWGzQ?Aq(}~LO=EJKxb"><field name="NAME">ball</field><field name="edgetype">top</field><value name="speed"><block type="variables_get" id="3:IeWUB4V_XK2)R`W8z|"><field name="VAR">ball speed</field></block></value><next><block type="sprite_intersect_sprite_bounce" id="RU[m-Iy{bMr%/3SC_(10"><field name="NAME">ball</field><field name="OTHER">paddle</field><value name="speed"><block type="variables_get" id="/2NpW%:{2kC,sB|x]qF%"><field name="VAR">ball speed</field></block></value><value name="other speed"><block type="math_number" id="XJ`#CT7ri86l+6Pq$}(`"><field name="NUM">0</field></block></value><next><block type="sprite_move" id="pRlz[$U8n5[:|%eU3Ax-"><field name="NAME">ball</field><value name="value"><block type="variables_get" id="Q:b%N-.b8/OuA~$luBeE"><field name="VAR">ball speed</field></block></value><next><block type="controls_if" id="/EWjHr@D0AF:GL_;^ULw"><value name="IF0"><block type="logic_compare" id="(E/0?OjT?lOTAz`olrzY"><field name="OP">EQ</field><value name="A"><block type="sprite_intersect_edge" id="*gtm33Fg]%CxFhL!4?n#"><field name="NAME">ball</field><field name="edgetype">bottom</field></block></value><value name="B"><block type="text" id="v)(/rU~VLP:tY1(c-.MI"><field name="TEXT">bottom</field></block></value></block></value><statement name="DO0"><block type="procedures_callnoreturn" id="#j32;ycQXbcSm$msOB24"><mutation name="reset ball"></mutation></block></statement></block></next></block></next></block></next></block></next></block></statement></block></statement><next><block type="set_interval" id="N|rD+[*/5xLMS(h)@]nH"><field name="timeout">500</field><statement name="statements"><block type="force_ui_update" id="x=*#HM8Q[:k0/oRksbl["></block></statement></block></next></block></next></block></next></block></next></block></next></block></statement></block></next></block><block type="procedures_defnoreturn" id="lW;7,tW4j?gMQVy_v`CI" x="-618" y="-669"><field name="NAME">reset ball</field><comment pinned="false" h="80" w="160">Describe this function...</comment><statement name="STACK"><block type="sprite_set_x" id="kiI}/Ko@TG/k%F1pJURb"><field name="NAME">ball</field><value name="value"><block type="math_number" id="hHZnqow%Mis%Bem]qqj$"><field name="NUM">102</field></block></value><next><block type="sprite_set_y" id="y6_}L67~ARp`n,hay1P["><field name="NAME">ball</field><value name="value"><block type="math_number" id="7(hcVh29T7$fo5eA.f}K"><field name="NUM">101</field></block></value><next><block type="variables_set" id="odb#IUr+R[!9pxVZPz99"><field name="VAR">initialangle</field><value name="VALUE"><block type="math_random_int" id=":{KaMhEQ7]1e)eSE,8Y!"><value name="FROM"><shadow type="math_number" id="IUqH2$IQz8pNto1aiDDp"><field name="NUM">95</field></shadow></value><value name="TO"><shadow type="math_number" id="R#:~(Bdtz2?)4|rL,00*"><field name="NUM">265</field></shadow></value></block></value><next><block type="sprite_set_direction" id="*M4RWlo}uAh36j)VQVq@"><field name="NAME">ball</field><value name="value"><block type="variables_get" id="v!6^P|*@0JpR])aCoPv/"><field name="VAR">initialangle</field></block></value></block></next></block></next></block></next></block></statement></block><block type="procedures_defreturn" id="fo#/C5~(6?:V3eo|lC5/" x="393" y="-583"><mutation><arg name="direction"></arg><arg name="normal"></arg></mutation><field name="NAME">reflect</field><comment pinned="false" h="80" w="160">Describe this function...</comment><value name="RETURN"><block type="math_arithmetic" id="TaOT[Nn;d-DN=bZ`Z@o3"><field name="OP">MINUS</field><value name="A"><shadow type="math_number" id="?)f8})aC/gD1LuD*ed4S"><field name="NUM">1</field></shadow><block type="math_arithmetic" id=";wUL:@:(*Q7?8HER_/ZW"><field name="OP">MINUS</field><value name="A"><shadow type="math_number" id="Zkf.Hgo%Lb1HC(IpnWsp"><field name="NUM">1</field></shadow><block type="math_arithmetic" id="@Z!$Aiyt19$pXd3[~pDc"><field name="OP">MULTIPLY</field><value name="A"><shadow type="math_number" id="{?Pr6h*(+63XV),J{[Jg"><field name="NUM">2</field></shadow></value><value name="B"><shadow type="math_number" id="!J{*S!xU3i$WDI$^Z]N;"><field name="NUM">1</field></shadow><block type="variables_get" id=";;!7}cKnymS1}~E?z62h"><field name="VAR">normal</field></block></value></block></value><value name="B"><shadow type="math_number" id="3NHIl31Yjl1io{KD/0CA"><field name="NUM">1</field></shadow><block type="variables_get" id="~!85;jg^xyN}H3O)L#!t"><field name="VAR">direction</field></block></value></block></value><value name="B"><shadow type="math_number" id="rGX+LE8i`r:nnL#[V_!x"><field name="NUM">180</field></shadow></value></block></value></block><block type="math_number" id="L|1%Q~7uh;GbjV;n^h!7" x="263" y="-425"><field name="NUM">315</field></block><block type="math_random_int" id="clYqZli]E6bWb;nl2Ltd" x="235" y="-391"><value name="FROM"><shadow type="math_number" id="Qzb3(vWulyFIySkgw(b="><field name="NUM">95</field></shadow></value><value name="TO"><shadow type="math_number" id="dfIs5d{458Q~{oe(!4XL"><field name="NUM">265</field></shadow></value></block><block type="text" id="-PjV-Y;J+u#S(H@/k/b," x="771" y="-246"><field name="TEXT">, </field></block><block type="canvas_get_height" id="aWf*Mm2~%`G|Zqm:AWmP" x="794" y="-180"><field name="NAME">canvas</field></block><block type="canvas_get_width" id="8-TYt~Qc~Q%/,?pI#|UD" x="756" y="-118"><field name="NAME">canvas</field></block><block type="user_interface" id="!Yn}z9vjZ$A:X]_/},!(" x="-88" y="169"><field name="theme">firstTheme</field><statement name="elements"><block type="friendly_group_element" id="5flo{SGvk{zz|^-Y0pCO"><mutation items="NaN" desc="friendly_group_element" installed=""></mutation><field name="NAME"></field><field name="child direction">row</field><field name="isFlex">FALSE</field><field name="visual purpose">panel</field><statement name="children"><block type="friendly_text_element" id="/%4-OFF:yWTDu;T/q8+("><mutation items="NaN" desc="friendly_text_element" installed=""></mutation><field name="isFlex">FALSE</field><field name="visual purpose">label</field><value name="text value"><shadow type="text" id="_RzlRCymEP{pA6b{E/;*"><field name="TEXT">Lorem Ipsum</field></shadow><block type="text_join" id="H?aDB.N]gEa~ud#vYq8n"><mutation items="5"></mutation><value name="ADD0"><block type="variables_get" id="z8;*)?@G}thT}YYx9LQ6"><field name="VAR">initialangle</field></block></value><value name="ADD1"><block type="text" id="Ha^]FKDwsi+rA[nC/Y9F"><field name="TEXT">, </field></block></value><value name="ADD2"><block type="sprite_get_x" id="ZrMy/KU]Xs9fG+peQS.u"><field name="NAME">ball</field></block></value><value name="ADD3"><block type="text" id="i7r0@@PUKz}.H#15%=IT"><field name="TEXT">, </field></block></value><value name="ADD4"><block type="sprite_get_y" id="]OA2cw-;9:Uqgz.V#[q="><field name="NAME">ball</field></block></value></block></value></block></statement><next><block type="canvas_element" id="?5]|v|w4KErk~OGYu#,*"><mutation items="NaN" desc="canvas_element" installed=""></mutation><field name="NAME">canvas</field><field name="isFlex">TRUE</field><field name="visual purpose">none</field><statement name="children"><block type="sprite_element" id="V,DwKx{/Sbhd_O_grzO%"><mutation items="0" desc="sprite_element" installed=""></mutation><field name="NAME">ball</field><field name="width">50</field><field name="height">50</field><value name="URL"><block type="text" id="2/Xd_Wc*)]bRYs+W143p"><field name="TEXT">http://www.clker.com/cliparts/0/w/6/u/P/t/beachball-primary-md.png</field></block></value><next><block type="sprite_element" id="?s!3029B-bvFDc)TaJ{_"><mutation items="3" desc="sprite_element" installed="graphicType,color,style"></mutation><field name="NAME">paddle</field><field name="width">100</field><field name="height">10</field><field name="OProp_graphicType">rectangle</field></block></next></block></statement><next><block type="friendly_group_element" id="/5eO*a8@*;CJ#nh?KZoO"><mutation items="NaN" desc="friendly_group_element" installed=""></mutation><field name="NAME"></field><field name="child direction">row</field><field name="isFlex">FALSE</field><field name="visual purpose">panel</field><statement name="children"><block type="friendly_button_element" id="U]~?D~vglCP[[lvpV5QQ"><mutation items="NaN" desc="friendly_button_element" installed=""></mutation><field name="NAME"></field><field name="isFlex">TRUE</field><field name="visual purpose">small</field><statement name="child elements"><shadow type="friendly_text_element" id="RxT4$M;S)lvlXo{[9Tw7"><mutation items="NaN" desc="friendly_text_element" installed=""></mutation><field name="isFlex">FALSE</field><field name="visual purpose">button</field><value name="text value"><shadow type="text" id="-m.i]pEBvkyQfne84NDO"><field name="TEXT">left</field></shadow></value></shadow><block type="icon_content" id=".!;wf2sp98#1E}b39qJR"><field name="VALUE">undo</field><field name="SIZE">24</field><field name="SHADE">black</field></block></statement><statement name="onPress"><block type="sprite_rotate_left" id="U}^z,.n`6o*iP9SusFI5"><field name="NAME">ball</field><value name="value"><block type="math_number" id="hFCM%eVU0sZyN|2R;SL|"><field name="NUM">15</field></block></value></block></statement><next><block type="friendly_group_element" id="(5[q8vIxJNIFZjfJbvP!"><mutation items="NaN" desc="friendly_group_element" installed=""></mutation><field name="NAME"></field><field name="child direction">column</field><field name="isFlex">TRUE</field><field name="visual purpose">panel</field><statement name="children"><block type="friendly_button_element" id="lo*T^haROv//{3.lJW.t"><mutation items="NaN" desc="friendly_button_element" installed=""></mutation><field name="NAME"></field><field name="isFlex">FALSE</field><field name="visual purpose">small</field><statement name="child elements"><shadow type="friendly_text_element" id="D[#jnoI$ppGuk_hZLN@)"><mutation items="0" desc="friendly_text_element" installed=""></mutation><field name="isFlex">FALSE</field><field name="visual purpose">button</field><value name="text value"><shadow type="text" id="!w.;a$02,UZTEFe?kZWH"><field name="TEXT">reset</field></shadow></value></shadow></statement><statement name="onPress"><block type="procedures_callnoreturn" id="I]ynW_Qy0$bX1%AM1+sG"><mutation name="reset ball"></mutation></block></statement><next><block type="friendly_button_element" id="wGbjsmvSwub*zGoF0fd("><mutation items="NaN" desc="friendly_button_element" installed=""></mutation><field name="NAME"></field><field name="isFlex">FALSE</field><field name="visual purpose">small</field><statement name="child elements"><shadow type="friendly_text_element" id="V_G/R=b)E?WH!HsK$tyD"><mutation items="NaN" desc="friendly_text_element" installed=""></mutation><field name="isFlex">FALSE</field><field name="visual purpose">button</field><value name="text value"><shadow type="text" id="q2PbLc7h`|^|BI67+jGj"><field name="TEXT">stop</field></shadow></value></shadow></statement><statement name="onPress"><block type="variables_set" id="=P=43+i_1.~Dc[#JJaLz"><field name="VAR">should go</field><value name="VALUE"><block type="logic_boolean" id=":Ppz~`gboUROaFPoU|0L"><field name="BOOL">FALSE</field></block></value></block></statement></block></next></block></statement><next><block type="friendly_button_element" id="m3H+@kaF3(=K3FK8.en;"><mutation items="NaN" desc="friendly_button_element" installed=""></mutation><field name="NAME"></field><field name="isFlex">TRUE</field><field name="visual purpose">small</field><statement name="child elements"><shadow type="friendly_text_element" id="+/]wA])v1GZO5mKZ8gz+"><mutation items="NaN" desc="friendly_text_element" installed=""></mutation><field name="isFlex">FALSE</field><field name="visual purpose">button</field><value name="text value"><shadow type="text" id="44nU$[_;B1OFH#0xiygW"><field name="TEXT">Button</field></shadow></value></shadow><block type="icon_content" id="!!9v5+0oF;y/3{/7_ivk"><field name="VALUE">redo</field><field name="SIZE">24</field><field name="SHADE">black</field></block></statement><statement name="onPress"><block type="sprite_rotate_right" id="aV.WU:EO2t:wU1Hc*R_K"><field name="NAME">ball</field><value name="value"><block type="math_number" id="x~_0)68)W[c#%x*sYR]o"><field name="NUM">15</field></block></value></block></statement></block></next></block></next></block></statement></block></next></block></next></block></statement></block></xml>